{"returnPhrase":["hound"],"query":"hound","errorCode":"0","l":"en2zh-CHS","tSpeakUrl":"https://openapi.youdao.com/ttsapi?q=%E7%8C%8E%E7%8A%AC&langType=zh-CHS&sign=07EE918624AA26A09B67564B3EE38DCD&salt=1679934086075&voice=4&format=mp3&appKey=2abf9bd7cbe89bc8&ttsVoiceStrict=false","web":[{"value":["探长","猎犬","卑鄙的人","角鲨"],"key":"Hound"},{"value":["依比沙猎犬","伊比赞猎犬","伊比莎猎犬","艾比赞猎犬"],"key":"Ibizan Hound"},{"value":["法老王猎犬","法老猎犬","法老王猎狗"],"key":"Pharaoh Hound"}],"requestId":"d3bdec58-b146-4f58-bb8d-40e1935c0f8a","translation":["猎犬"],"mTerminalDict":{"url":"https://m.youdao.com/m/result?lang=en&word=hound"},"dict":{"url":"yddict://m.youdao.com/dict?le=eng&q=hound"},"webdict":{"url":"http://mobile.youdao.com/dict?le=eng&q=hound"},"basic":{"exam_type":["CET6","考研"],"us-phonetic":"haʊnd","phonetic":"haʊnd","uk-phonetic":"haʊnd","wfs":[{"wf":{"name":"复数","value":"hounds"}},{"wf":{"name":"第三人称单数","value":"hounds"}},{"wf":{"name":"现在分词","value":"hounding"}},{"wf":{"name":"过去式","value":"hounded"}},{"wf":{"name":"过去分词","value":"hounded"}}],"uk-speech":"https://openapi.youdao.com/ttsapi?q=hound&langType=en&sign=6C4624A8B53647D86E4D241F315CA98A&salt=1679934086075&voice=5&format=mp3&appKey=2abf9bd7cbe89bc8&ttsVoiceStrict=false","explains":["n. 猎犬；<非正式>卑鄙的人","v. 纠缠，烦扰；（用猎犬）追猎，追逐；激励"],"us-speech":"https://openapi.youdao.com/ttsapi?q=hound&langType=en&sign=6C4624A8B53647D86E4D241F315CA98A&salt=1679934086075&voice=6&format=mp3&appKey=2abf9bd7cbe89bc8&ttsVoiceStrict=false"},"isWord":true,"speakUrl":"https://openapi.youdao.com/ttsapi?q=hound&langType=en-USA&sign=6C4624A8B53647D86E4D241F315CA98A&salt=1679934086075&voice=4&format=mp3&appKey=2abf9bd7cbe89bc8&ttsVoiceStrict=false"}