{"returnPhrase":["vice"],"query":"vice","errorCode":"0","l":"en2zh-CHS","tSpeakUrl":"https://openapi.youdao.com/ttsapi?q=%E5%89%AF&langType=zh-CHS&sign=ABB5C39F6094277387BBA3B9550D25BD&salt=1678243646066&voice=4&format=mp3&appKey=2abf9bd7cbe89bc8&ttsVoiceStrict=false","web":[{"value":["虎钳","台钳","老虎钳"],"key":"vice"},{"value":["迈阿密风云","迈阿密风暴","迈阿密天龙","迈阿密罪恶"],"key":"Miami Vice"},{"value":["副校长","副总裁","大学副校长","副院长"],"key":"vice-president"}],"requestId":"57634cc9-aa65-4d53-946a-f55283e1fe51","translation":["副"],"mTerminalDict":{"url":"https://m.youdao.com/m/result?lang=en&word=vice"},"dict":{"url":"yddict://m.youdao.com/dict?le=eng&q=vice"},"webdict":{"url":"http://mobile.youdao.com/dict?le=eng&q=vice"},"basic":{"exam_type":["高中","CET6","考研","TOEFL"],"us-phonetic":"vaɪs","phonetic":"vaɪs","uk-phonetic":"vaɪs","wfs":[{"wf":{"name":"复数","value":"vices"}},{"wf":{"name":"第三人称单数","value":"vices"}},{"wf":{"name":"现在分词","value":"vicing"}},{"wf":{"name":"过去式","value":"viced"}},{"wf":{"name":"过去分词","value":"viced"}}],"uk-speech":"https://openapi.youdao.com/ttsapi?q=vice&langType=en&sign=A72A5E35DE4580F17F02D1441B584964&salt=1678243646066&voice=5&format=mp3&appKey=2abf9bd7cbe89bc8&ttsVoiceStrict=false","explains":["n. 堕落，邪恶；小毛病，坏习惯；（与性或毒品有关的）罪行，道德败坏行为；老虎钳（同 vise）；<非正式>代理人，任副职者；（尤指马厩里马因厌倦而出现的）劣性，恶癖","v. 握住，钳紧","adj. 副的；代替的，代理的","prep. 代替","【名】 （Vice）（塞）维采（人名）"],"us-speech":"https://openapi.youdao.com/ttsapi?q=vice&langType=en&sign=A72A5E35DE4580F17F02D1441B584964&salt=1678243646066&voice=6&format=mp3&appKey=2abf9bd7cbe89bc8&ttsVoiceStrict=false"},"isWord":true,"speakUrl":"https://openapi.youdao.com/ttsapi?q=vice&langType=en-USA&sign=A72A5E35DE4580F17F02D1441B584964&salt=1678243646066&voice=4&format=mp3&appKey=2abf9bd7cbe89bc8&ttsVoiceStrict=false"}